<?xml version="1.0" encoding="UTF-8"?>
<tv generator-info-name="WebGrab+Plus/w MDB &amp; REX Postprocess -- version  V3.2.0.0 -- Jan van Straaten" generator-info-url="http://www.webgrabplus.com">
  <channel id="beIN Sports Xtra Ñ.us">
    <display-name lang="en">US | beIN Sports Xtra Ñ</display-name>
    <icon src="https://epg-pp.beinsports.com/us_sports/beinx-es1.png" />
    <url>http://www.beinxtraespanol.com</url>
  </channel>
  <programme start="20220907000000 +0000" stop="20220907010000 +0000" channel="beIN Sports Xtra Ñ.us">
    <title lang="en">La octava, noticiero deportivo desde México</title>
    <sub-title lang="en">News</sub-title>
  </programme>
  <programme start="20220907010000 +0000" stop="20220907030000 +0000" channel="beIN Sports Xtra Ñ.us">
    <title lang="en">Deportivo Táchira vs. Palmeiras</title>
    <sub-title lang="en">Lo mejor de Palmeiras</sub-title>
    <category lang="en">Soccer</category>
  </programme>
  <programme start="20220907030000 +0000" stop="20220907050000 +0000" channel="beIN Sports Xtra Ñ.us">
    <title lang="en">Palmeiras vs. Independiente del Valle</title>
    <sub-title lang="en">Lo mejor de Palmeiras</sub-title>
    <category lang="en">Soccer</category>
  </programme>
  <programme start="20220907050000 +0000" stop="20220907060000 +0000" channel="beIN Sports Xtra Ñ.us">
    <title lang="en">La octava, noticiero deportivo desde México</title>
    <sub-title lang="en">News</sub-title>
  </programme>
  <programme start="20220907060000 +0000" stop="20220907080000 +0000" channel="beIN Sports Xtra Ñ.us">
    <title lang="en">Corinthians vs. Flamengo</title>
    <sub-title lang="en">Lo mejor de Flamengo</sub-title>
    <category lang="en">Sports</category>
  </programme>
  <programme start="20220907080000 +0000" stop="20220907083000 +0000" channel="beIN Sports Xtra Ñ.us">
    <title lang="en">Universidad Católica (CHI) vs. Flamengo</title>
    <sub-title lang="en">Lo mejor de Flamengo</sub-title>
    <category lang="en">Sports</category>
  </programme>
  <programme start="20220907083000 +0000" stop="20220907103000 +0000" channel="beIN Sports Xtra Ñ.us">
    <title lang="en">Flamengo vs. Deportes Tolima</title>
    <sub-title lang="en">Lo mejor de Flamengo</sub-title>
    <category lang="en">Sports</category>
  </programme>
  <programme start="20220907103000 +0000" stop="20220907113000 +0000" channel="beIN Sports Xtra Ñ.us">
    <title lang="en">Flamengo vs. River</title>
    <sub-title lang="en">Lo mejor de Flamengo</sub-title>
    <category lang="en">Sports</category>
  </programme>
  <programme start="20220907113000 +0000" stop="20220907133000 +0000" channel="beIN Sports Xtra Ñ.us">
    <title lang="en">Flamengo vs. Unión La Calera</title>
    <sub-title lang="en">Lo mejor de Flamengo</sub-title>
    <category lang="en">Sports</category>
  </programme>
  <programme start="20220907133000 +0000" stop="20220907140000 +0000" channel="beIN Sports Xtra Ñ.us">
    <title lang="en">Defensa y Justicia vs. Flamengo</title>
    <sub-title lang="en">Lo mejor de Flamengo</sub-title>
    <category lang="en">Sports</category>
  </programme>
  <programme start="20220907140000 +0000" stop="20220907143000 +0000" channel="beIN Sports Xtra Ñ.us">
    <title lang="en">Barcelona vs. Flamengo</title>
    <sub-title lang="en">Lo mejor de Flamengo</sub-title>
    <category lang="en">Sports</category>
  </programme>
  <programme start="20220907143000 +0000" stop="20220907150000 +0000" channel="beIN Sports Xtra Ñ.us">
    <title lang="en">Junior vs. Flamengo</title>
    <sub-title lang="en">Lo mejor de Flamengo</sub-title>
    <category lang="en">Sports</category>
  </programme>
  <programme start="20220907150000 +0000" stop="20220907153000 +0000" channel="beIN Sports Xtra Ñ.us">
    <title lang="en">Flamengo vs. Defensa y Justicia</title>
    <sub-title lang="en">Lo mejor de Flamengo</sub-title>
    <category lang="en">Sports</category>
  </programme>
  <programme start="20220907153000 +0000" stop="20220907160000 +0000" channel="beIN Sports Xtra Ñ.us">
    <title lang="en">Welcome to Qatar</title>
    <category lang="en">Sports</category>
  </programme>
  <programme start="20220907160000 +0000" stop="20220907170000 +0000" channel="beIN Sports Xtra Ñ.us">
    <title lang="en">La octava, noticiero deportivo desde México</title>
    <sub-title lang="en">News</sub-title>
  </programme>
  <programme start="20220907170000 +0000" stop="20220907173000 +0000" channel="beIN Sports Xtra Ñ.us">
    <title lang="en">Gabriel Barbosa: Flamengo vs. River Plate</title>
    <sub-title lang="en">Stars of Qatar</sub-title>
    <category lang="en">Sports</category>
  </programme>
  <programme start="20220907173000 +0000" stop="20220907180000 +0000" channel="beIN Sports Xtra Ñ.us">
    <title lang="en">Quarterfinal (1st Leg)</title>
    <sub-title lang="en">Copa Sudamericana Highlight Show</sub-title>
    <category lang="en">Sports</category>
  </programme>
  <programme start="20220907180000 +0000" stop="20220907183000 +0000" channel="beIN Sports Xtra Ñ.us">
    <title lang="en">Quarterfinals (2nd Leg)</title>
    <sub-title lang="en">Copa Sudamericana Highlight Show</sub-title>
    <category lang="en">Sports</category>
  </programme>
  <programme start="20220907183000 +0000" stop="20220907190000 +0000" channel="beIN Sports Xtra Ñ.us">
    <title lang="en">Copa Sudamericana Highlight Show</title>
    <category lang="en">Sports</category>
  </programme>
  <programme start="20220907190000 +0000" stop="20220907192000 +0000" channel="beIN Sports Xtra Ñ.us">
    <title lang="en">Welcome to Qatar</title>
    <category lang="en">Sports</category>
  </programme>
  <programme start="20220907192000 +0000" stop="20220907213000 +0000" channel="beIN Sports Xtra Ñ.us">
    <title lang="en">Melgar vs. Independiente del Valle</title>
    <sub-title lang="en">Fútbol CONMEBOL Sudamericana</sub-title>
    <category lang="en">Soccer</category>
  </programme>
  <programme start="20220907213000 +0000" stop="20220907220000 +0000" channel="beIN Sports Xtra Ñ.us">
    <title lang="en">Lo mejor de la Ligue 1</title>
    <category lang="en">Soccer</category>
  </programme>
  <programme start="20220907220000 +0000" stop="20220907223000 +0000" channel="beIN Sports Xtra Ñ.us">
    <title lang="en">2022-2023: Nice vs. Monaco</title>
    <sub-title lang="en">Lo mejor de la Ligue 1</sub-title>
    <category lang="en">Soccer</category>
  </programme>
  <programme start="20220907223000 +0000" stop="20220907225000 +0000" channel="beIN Sports Xtra Ñ.us">
    <title lang="en">2022-2023: Toulouse vs. Paris Saint-Germain</title>
    <sub-title lang="en">Lo mejor de la Ligue 1</sub-title>
    <category lang="en">Soccer</category>
  </programme>
  <programme start="20220907225000 +0000" stop="20220907233000 +0000" channel="beIN Sports Xtra Ñ.us">
    <title lang="en">2022-2023: Auxerre vs. Marseille</title>
    <sub-title lang="en">Lo mejor de la Ligue 1</sub-title>
    <category lang="en">Soccer</category>
  </programme>
  <programme start="20220907233000 +0000" stop="20220908000000 +0000" channel="beIN Sports Xtra Ñ.us">
    <title lang="en">2022-2023: Lyon vs. Angers</title>
    <sub-title lang="en">Lo mejor de la Ligue 1</sub-title>
    <category lang="en">Soccer</category>
  </programme>
</tv>